docusign/__init__.py
docusign/exception.py
docusign/logger.py
docusign/serializer.py
docusign/helper/__init__.py
docusign/helper/ds_client.py
docusign/helper/token.py
docusign/service/__init__.py
docusign/service/docusign_service.py
docusign/service/envelope_service.py
docusign/service/http_service.py
docusign/service/template_service.py
docusign/service/token_service.py
DocusignRestClient-0.0.12.dist-info/LICENSE
DocusignRestClient-0.0.12.dist-info/METADATA
DocusignRestClient-0.0.12.dist-info/WHEEL
DocusignRestClient-0.0.12.dist-info/top_level.txt
DocusignRestClient-0.0.12.dist-info/RECORD
