Metadata-Version: 2.1
Name: DocusignRestClient
Version: 0.0.12
Summary: Docusign Api Client Python package
Home-page: https://github.com/blueromans/Docusign-Python-Client.git
Author: Yaşar Özyurt
Author-email: blueromans@gmail.com
Project-URL: Bug Tracker, https://github.com/blueromans/Docusign-Python-Client.git/issues
Classifier: Programming Language :: Python :: 3
Classifier: License :: OSI Approved :: MIT License
Classifier: Operating System :: OS Independent
Requires-Python: >=3.6
License-File: LICENSE
Requires-Dist: requests
Requires-Dist: python-dotenv
Requires-Dist: docusign-esign
